{
  "generator-jhipster": {
    "jhipsterVersion": "3.12.2",
    "baseName": "smartwms",
    "packageName": "com.kinnsoft.api",
    "packageFolder": "com/kinnsoft/api",
    "serverPort": "8080",
    "authenticationType": "oauth2",
    "hibernateCache": "no",
    "clusteredHttpSession": false,
    "websocket": false,
    "databaseType": "sql",
    "devDatabaseType": "h2Disk",
    "prodDatabaseType": "mysql",
    "searchEngine": false,
    "messageBroker": false,
    "buildTool": "gradle",
    "enableSocialSignIn": false,
    "enableTranslation": true,
    "nativeLanguage": "zh-cn",
    "languages": [
      "zh-cn",
      "en"
    ]
  }
}